{"id": "2094", "status": "C", "NewGame": "0", "drawDate": "03/01/2017", "p1HorseNo": "10", "p2HorseNo": "9", "p3HorseNo": "1", "drawNo": "4477/17", "starterHorseList": ["13", "11", "7", "5", "4", "6", "12", "8", "3", "2"], "consolidateList": ["5764", "5955", "1850", "4254", "4594", "7454", "4445", "3470", "3541", "4276"], "starterList": ["0792", "6179", "1884", "8550", "3096", "4358", "4607", "6341", "2430", "9292"], "1+3DJackpot1": "13,511,143.60", "1+3DJackpot2": "515,384.90", "dmcJackpot1": "6,322,157.20", "dmcJackpot2": "258,421.90", "3DJackpot": "772,418.70", "1+3DJackpotWinning1": "1", "1+3DJackpotWinning2": "1", "3DJackpotWinning": "0", "dmcJackpotWinning1": "0", "dmcJackpotWinning2": "0", "drawVenue": "PERAK TURF CLUB", "raceNo": "6", "raceVenue": "HONG KONG JOCKEY CLUB", "p1": "2077", "p2": "7059", "p3": "7349", "consolidateList3p3d": [], "starterList3p3d": [], "p13p3d": "", "p23p3d": "", "p33p3d": "", "zodiac3dp1": "", "zodiac3dp2": "", "zodiac3dp3": "", "3+3DBonusp1": "300,000.00", "3+3DBonusp2": "100,000.00", "3+3DBonusp3": "30,000.00", "3+3DBonusp1Winning": "0", "3+3DBonusp2Winning": "0", "3+3DBonusp3Winning": "0", "winninghistoryconsolidateList": ["07/06/2015", "27/01/2013", "23/08/2015", "04/07/2010", "13/02/2016", "05/03/2016", "23/07/2014", "03/07/2016", "14/02/2016", "16/04/2016"], "winninghistoryconsolidateListPrize": ["3rd", "Consolation", "Starter", "Starter", "2nd", "3rd", "Starter", "Consolation", "Consolation", "Consolation"], "winninghistorystarterList": ["16/07/2014", "31/05/2016", "05/12/2009", "06/11/2016", "14/08/2016", "10/08/2016", "13/11/2013", "27/01/2016", "07/03/2015", "26/10/2016"], "winninghistorystarterListPrize": ["Starter", "1st", "Starter", "1st", "Starter", "3rd", "Consolation", "1st", "Consolation", "Consolation"], "winninghistoryconsolidateList3p3d": ["-", "-", "-", "-", "-", "-", "-", "-", "-", "-"], "winninghistoryconsolidateList3p3dPrize": ["-", "-", "-", "-", "-", "-", "-", "-", "-", "-"], "winninghistorystarterList3p3d": ["-", "-", "-", "-", "-", "-", "-", "-", "-", "-"], "winninghistorystaterList3p3dPrize": ["-", "-", "-", "-", "-", "-", "-", "-", "-", "-"], "winninghistoryp1": "01/05/2016", "winninghistoryp1prize": "Starter", "winninghistoryp2": "30/12/2014", "winninghistoryp2prize": "Starter", "winninghistoryp3": "03/03/2015", "winninghistoryp3prize": "1st", "winninghistoryp13d": "23/10/2016", "winninghistoryp13dprize": "3rd", "winninghistoryp23d": "27/04/2014", "winninghistoryp23dprize": "1st", "winninghistoryp33d": "22/10/2016", "winninghistoryp33dprize": "3rd", "winninghistoryp13p3d": "-", "winninghistoryp13p3dprize": "-", "winninghistoryp23p3d": "-", "winninghistoryp23p3dprize": "-", "winninghistoryp33p3d": "-", "winninghistoryp33p3dprize": "-"}