{"id": "2137", "status": "C", "NewGame": "0", "drawDate": "29/03/2017", "p1HorseNo": "12", "p2HorseNo": "1", "p3HorseNo": "4", "drawNo": "4520/17", "starterHorseList": ["13", "8", "2", "6", "7", "5", "3", "9", "11", "10"], "consolidateList": ["1324", "4848", "3249", "7783", "4989", "4416", "8761", "0731", "5479", "0954"], "starterList": ["7375", "4809", "0324", "9979", "7701", "2365", "6000", "5996", "6681", "2126"], "1+3DJackpot1": "22,993,740.90", "1+3DJackpot2": "117,669.80", "dmcJackpot1": "7,042,136.40", "dmcJackpot2": "100,000.00", "3DJackpot": "685,219.70", "1+3DJackpotWinning1": "0", "1+3DJackpotWinning2": "1", "3DJackpotWinning": "0", "dmcJackpotWinning1": "0", "dmcJackpotWinning2": "0", "drawVenue": "PERAK TURF CLUB", "raceNo": "8", "raceVenue": "HONG KONG JOCKEY CLUB", "p1": "8336", "p2": "6001", "p3": "1444", "consolidateList3p3d": [], "starterList3p3d": [], "p13p3d": "", "p23p3d": "", "p33p3d": "", "zodiac3dp1": "", "zodiac3dp2": "", "zodiac3dp3": "", "3+3DBonusp1": "300,000.00", "3+3DBonusp2": "100,000.00", "3+3DBonusp3": "30,000.00", "3+3DBonusp1Winning": "0", "3+3DBonusp2Winning": "0", "3+3DBonusp3Winning": "0", "winninghistoryconsolidateList": ["23/08/2015", "05/02/2017", "02/04/2011", "01/03/2016", "03/05/2016", "05/10/2016", "19/04/2015", "23/04/2016", "09/12/2012", "26/08/2015"], "winninghistoryconsolidateListPrize": ["Consolation", "Consolation", "Consolation", "Starter", "Starter", "Starter", "Consolation", "1st", "Starter", "Starter"], "winninghistorystarterList": ["04/11/2015", "13/12/2014", "10/12/2014", "01/02/2017", "08/02/2017", "14/05/2016", "25/04/2015", "02/11/2013", "04/03/2017", "01/12/2013"], "winninghistorystarterListPrize": ["Consolation", "Starter", "Consolation", "Consolation", "Starter", "Consolation", "Starter", "Consolation", "Starter", "Starter"], "winninghistoryconsolidateList3p3d": ["-", "-", "-", "-", "-", "-", "-", "-", "-", "-"], "winninghistoryconsolidateList3p3dPrize": ["-", "-", "-", "-", "-", "-", "-", "-", "-", "-"], "winninghistorystarterList3p3d": ["-", "-", "-", "-", "-", "-", "-", "-", "-", "-"], "winninghistorystaterList3p3dPrize": ["-", "-", "-", "-", "-", "-", "-", "-", "-", "-"], "winninghistoryp1": "13/04/2016", "winninghistoryp1prize": "Consolation", "winninghistoryp2": "21/12/2016", "winninghistoryp2prize": "Starter", "winninghistoryp3": "24/09/2016", "winninghistoryp3prize": "Starter", "winninghistoryp13d": "17/01/2017", "winninghistoryp13dprize": "3rd", "winninghistoryp23d": "30/11/2016", "winninghistoryp23dprize": "2nd", "winninghistoryp33d": "01/01/2017", "winninghistoryp33dprize": "1st", "winninghistoryp13p3d": "-", "winninghistoryp13p3dprize": "-", "winninghistoryp23p3d": "-", "winninghistoryp23p3dprize": "-", "winninghistoryp33p3d": "-", "winninghistoryp33p3dprize": "-"}