{"id": "2206", "status": "C", "NewGame": "0", "drawDate": "23/08/2017", "p1HorseNo": "3", "p2HorseNo": "5", "p3HorseNo": "1", "drawNo": "4589/17", "starterHorseList": ["13", "12", "2", "7", "10", "11", "8", "4", "9", "6"], "consolidateList": ["1890", "7747", "0501", "1295", "7913", "9467", "8252", "1642", "6029", "9904"], "starterList": ["0158", "3949", "3670", "8141", "0129", "0350", "0357", "6079", "2394", "1583"], "1+3DJackpot1": "8,292,295.90", "1+3DJackpot2": "100,000.00", "dmcJackpot1": "8,331,675.20", "dmcJackpot2": "268,160.70", "3DJackpot": "803,494.30", "1+3DJackpotWinning1": "0", "1+3DJackpotWinning2": "0", "3DJackpotWinning": "0", "dmcJackpotWinning1": "0", "dmcJackpotWinning2": "0", "drawVenue": "PERAK TURF CLUB", "raceNo": "2", "raceVenue": "MACAU JOCKEY CLUB", "p1": "0658", "p2": "6078", "p3": "3779", "consolidateList3p3d": [], "starterList3p3d": [], "p13p3d": "", "p23p3d": "", "p33p3d": "", "zodiac3dp1": "", "zodiac3dp2": "", "zodiac3dp3": "", "3+3DBonusp1": "300,000.00", "3+3DBonusp2": "100,000.00", "3+3DBonusp3": "30,000.00", "3+3DBonusp1Winning": "0", "3+3DBonusp2Winning": "0", "3+3DBonusp3Winning": "0", "winninghistoryconsolidateList": ["14/09/2013", "04/04/2017", "27/12/2016", "11/02/2009", "22/03/2017", "20/02/2016", "23/11/2016", "18/04/2015", "24/01/2017", "09/05/2015"], "winninghistoryconsolidateListPrize": ["Consolation", "Starter", "3rd", "1st", "Starter", "Consolation", "Consolation", "Consolation", "Starter", "Starter"], "winninghistorystarterList": ["20/01/2013", "06/11/2011", "23/07/2017", "07/11/2015", "26/06/2011", "02/09/2012", "06/01/2015", "28/12/2016", "11/12/2016", "31/05/2017"], "winninghistorystarterListPrize": ["Consolation", "Starter", "Consolation", "1st", "Consolation", "Consolation", "Starter", "Starter", "Consolation", "Consolation"], "winninghistoryconsolidateList3p3d": ["-", "-", "-", "-", "-", "-", "-", "-", "-", "-"], "winninghistoryconsolidateList3p3dPrize": ["-", "-", "-", "-", "-", "-", "-", "-", "-", "-"], "winninghistorystarterList3p3d": ["-", "-", "-", "-", "-", "-", "-", "-", "-", "-"], "winninghistorystaterList3p3dPrize": ["-", "-", "-", "-", "-", "-", "-", "-", "-", "-"], "winninghistoryp1": "24/12/2016", "winninghistoryp1prize": "Consolation", "winninghistoryp2": "04/04/2017", "winninghistoryp2prize": "Starter", "winninghistoryp3": "26/03/2017", "winninghistoryp3prize": "Consolation", "winninghistoryp13d": "09/05/2015", "winninghistoryp13dprize": "3rd", "winninghistoryp23d": "14/10/2015", "winninghistoryp23dprize": "3rd", "winninghistoryp33d": "09/04/2016", "winninghistoryp33dprize": "2nd", "winninghistoryp13p3d": "-", "winninghistoryp13p3dprize": "-", "winninghistoryp23p3d": "-", "winninghistoryp23p3dprize": "-", "winninghistoryp33p3d": "-", "winninghistoryp33p3dprize": "-"}