{"id": "2228", "status": "C", "NewGame": "0", "drawDate": "04/10/2017", "p1HorseNo": "11", "p2HorseNo": "2", "p3HorseNo": "8", "drawNo": "4611/17", "starterHorseList": ["13", "12", "5", "4", "3", "6", "7", "1", "10", "9"], "consolidateList": ["9982", "0443", "4874", "9853", "3113", "4191", "8007", "6871", "4260", "0011"], "starterList": ["6871", "0999", "8612", "8768", "7812", "9033", "1430", "9410", "0199", "4887"], "1+3DJackpot1": "4,761,486.90", "1+3DJackpot2": "431,453.70", "dmcJackpot1": "8,728,000.80", "dmcJackpot2": "347,425.80", "3DJackpot": "1,001,065.50", "1+3DJackpotWinning1": "0", "1+3DJackpotWinning2": "2", "3DJackpotWinning": "0", "dmcJackpotWinning1": "0", "dmcJackpotWinning2": "0", "drawVenue": "PERAK TURF CLUB", "raceNo": "5", "raceVenue": "HONG KONG JOCKEY CLUB", "p1": "2797", "p2": "3229", "p3": "9209", "consolidateList3p3d": [], "starterList3p3d": [], "p13p3d": "", "p23p3d": "", "p33p3d": "", "zodiac3dp1": "", "zodiac3dp2": "", "zodiac3dp3": "", "3+3DBonusp1": "300,000.00", "3+3DBonusp2": "100,000.00", "3+3DBonusp3": "30,000.00", "3+3DBonusp1Winning": "0", "3+3DBonusp2Winning": "0", "3+3DBonusp3Winning": "0", "winninghistoryconsolidateList": ["16/08/2017", "21/11/2015", "06/01/2016", "16/10/2016", "03/09/2016", "25/06/2017", "14/05/2017", "24/09/2017", "20/12/2014", "27/11/2010"], "winninghistoryconsolidateListPrize": ["Consolation", "3rd", "Starter", "Starter", "3rd", "Starter", "Consolation", "Consolation", "Starter", "Consolation"], "winninghistorystarterList": ["24/09/2017", "30/09/2017", "27/12/2016", "21/09/2016", "21/08/2016", "12/08/2015", "17/02/2016", "25/06/2014", "16/04/2017", "04/03/2014"], "winninghistorystarterListPrize": ["Consolation", "Consolation", "Consolation", "Starter", "Consolation", "Starter", "Consolation", "Consolation", "Consolation", "Consolation"], "winninghistoryconsolidateList3p3d": ["-", "-", "-", "-", "-", "-", "-", "-", "-", "-"], "winninghistoryconsolidateList3p3dPrize": ["-", "-", "-", "-", "-", "-", "-", "-", "-", "-"], "winninghistorystarterList3p3d": ["-", "-", "-", "-", "-", "-", "-", "-", "-", "-"], "winninghistorystaterList3p3dPrize": ["-", "-", "-", "-", "-", "-", "-", "-", "-", "-"], "winninghistoryp1": "06/01/2013", "winninghistoryp1prize": "Consolation", "winninghistoryp2": "20/09/2015", "winninghistoryp2prize": "Starter", "winninghistoryp3": "23/07/2014", "winninghistoryp3prize": "Starter", "winninghistoryp13d": "13/08/2017", "winninghistoryp13dprize": "3rd", "winninghistoryp23d": "11/02/2015", "winninghistoryp23dprize": "3rd", "winninghistoryp33d": "11/03/2017", "winninghistoryp33dprize": "3rd", "winninghistoryp13p3d": "-", "winninghistoryp13p3dprize": "-", "winninghistoryp23p3d": "-", "winninghistoryp23p3dprize": "-", "winninghistoryp33p3d": "-", "winninghistoryp33p3dprize": "-"}