{"id": "2291", "status": "C", "NewGame": "0", "drawDate": "10/02/2018", "p1HorseNo": "6", "p2HorseNo": "7", "p3HorseNo": "8", "drawNo": "4674/18", "starterHorseList": ["13", "10", "3", "9", "2", "4", "5", "1", "12", "11"], "consolidateList": ["2399", "6651", "0117", "0344", "5178", "2176", "0435", "7687", "8593", "2359"], "starterList": ["0348", "9589", "1541", "2870", "4626", "9638", "4678", "7496", "1140", "0396"], "1+3DJackpot1": "2,508,079.70", "1+3DJackpot2": "335,212.30", "dmcJackpot1": "9,994,599.10", "dmcJackpot2": "115,900.10", "3DJackpot": "690,674.40", "1+3DJackpotWinning1": "1", "1+3DJackpotWinning2": "0", "3DJackpotWinning": "1", "dmcJackpotWinning1": "0", "dmcJackpotWinning2": "0", "drawVenue": "PERAK TURF CLUB", "raceNo": "2", "raceVenue": "HONG KONG JOCKEY CLUB", "p1": "1603", "p2": "0759", "p3": "6072", "consolidateList3p3d": [], "starterList3p3d": [], "p13p3d": "", "p23p3d": "", "p33p3d": "", "zodiac3dp1": "", "zodiac3dp2": "", "zodiac3dp3": "", "3+3DBonusp1": "300,000.00", "3+3DBonusp2": "100,000.00", "3+3DBonusp3": "30,000.00", "3+3DBonusp1Winning": "0", "3+3DBonusp2Winning": "0", "3+3DBonusp3Winning": "0", "winninghistoryconsolidateList": ["16/06/2013", "23/11/2016", "17/12/2011", "06/07/2014", "31/01/2018", "23/08/2014", "26/06/2016", "06/09/2016", "24/07/2016", "16/07/2016"], "winninghistoryconsolidateListPrize": ["Consolation", "Starter", "Starter", "Consolation", "1st", "Starter", "Consolation", "Starter", "Consolation", "Consolation"], "winninghistorystarterList": ["29/09/2010", "18/06/2017", "03/10/2017", "26/06/2012", "30/03/2016", "29/12/2015", "20/09/2017", "05/06/2016", "10/09/2016", "07/10/2017"], "winninghistorystarterListPrize": ["Consolation", "Starter", "Consolation", "1st", "Starter", "Consolation", "Consolation", "Starter", "Starter", "Starter"], "winninghistoryconsolidateList3p3d": ["-", "-", "-", "-", "-", "-", "-", "-", "-", "-"], "winninghistoryconsolidateList3p3dPrize": ["-", "-", "-", "-", "-", "-", "-", "-", "-", "-"], "winninghistorystarterList3p3d": ["-", "-", "-", "-", "-", "-", "-", "-", "-", "-"], "winninghistorystaterList3p3dPrize": ["-", "-", "-", "-", "-", "-", "-", "-", "-", "-"], "winninghistoryp1": "17/04/2016", "winninghistoryp1prize": "Consolation", "winninghistoryp2": "10/02/2010", "winninghistoryp2prize": "Starter", "winninghistoryp3": "22/03/2017", "winninghistoryp3prize": "Starter", "winninghistoryp13d": "13/01/2018", "winninghistoryp13dprize": "3rd", "winninghistoryp23d": "20/01/2018", "winninghistoryp23dprize": "2nd", "winninghistoryp33d": "06/12/2014", "winninghistoryp33dprize": "3rd", "winninghistoryp13p3d": "-", "winninghistoryp13p3dprize": "-", "winninghistoryp23p3d": "-", "winninghistoryp23p3dprize": "-", "winninghistoryp33p3d": "-", "winninghistoryp33p3dprize": "-"}