{"id": "819", "status": "C", "NewGame": "0", "drawDate": "01/11/2009", "p1HorseNo": "", "p2HorseNo": "", "p3HorseNo": "", "drawNo": "3200/09", "starterHorseList": ["", "", "", "", "", "", "", "", "", ""], "consolidateList": ["0730", "0484", "8688", "0330", "6872", "9809", "9220", "8482", "3019", "9678"], "starterList": ["5597", "6862", "5384", "2391", "1515", "4597", "3429", "7868", "4748", "5407"], "1+3DJackpot1": "0.00", "1+3DJackpot2": "0.00", "dmcJackpot1": "0.00", "dmcJackpot2": "0.00", "3DJackpot": "0.00", "1+3DJackpotWinning1": "0", "1+3DJackpotWinning2": "0", "3DJackpotWinning": "0", "dmcJackpotWinning1": "0", "dmcJackpotWinning2": "0", "drawVenue": "SELANGOR TURF CLUB", "raceNo": "", "raceVenue": "", "p1": "7214", "p2": "1400", "p3": "9983", "consolidateList3p3d": [], "starterList3p3d": [], "p13p3d": "", "p23p3d": "", "p33p3d": "", "zodiac3dp1": "", "zodiac3dp2": "", "zodiac3dp3": "", "3+3DBonusp1": "300,000.00", "3+3DBonusp2": "100,000.00", "3+3DBonusp3": "30,000.00", "3+3DBonusp1Winning": "0", "3+3DBonusp2Winning": "0", "3+3DBonusp3Winning": "0", "winninghistoryconsolidateList": ["31/12/2008", "16/03/2008", "02/08/2008", "-", "12/11/2008", "03/12/2006", "13/09/2008", "17/01/2009", "-", "10/03/2009"], "winninghistoryconsolidateListPrize": ["1st", "Consolation", "Consolation", "-", "Consolation", "Consolation", "Consolation", "Consolation", "-", "Consolation"], "winninghistorystarterList": ["30/06/2007", "23/12/2007", "13/09/2009", "06/06/2009", "30/12/2008", "08/08/2007", "18/11/2006", "23/08/2009", "-", "14/07/2009"], "winninghistorystarterListPrize": ["Consolation", "1st", "Consolation", "Starter", "Starter", "Consolation", "Starter", "Consolation", "-", "Consolation"], "winninghistoryconsolidateList3p3d": ["-", "-", "-", "-", "-", "-", "-", "-", "-", "-"], "winninghistoryconsolidateList3p3dPrize": ["-", "-", "-", "-", "-", "-", "-", "-", "-", "-"], "winninghistorystarterList3p3d": ["-", "-", "-", "-", "-", "-", "-", "-", "-", "-"], "winninghistorystaterList3p3dPrize": ["-", "-", "-", "-", "-", "-", "-", "-", "-", "-"], "winninghistoryp1": "13/06/2007", "winninghistoryp1prize": "Consolation", "winninghistoryp2": "15/03/2009", "winninghistoryp2prize": "Consolation", "winninghistoryp3": "05/01/2005", "winninghistoryp3prize": "Consolation", "winninghistoryp13d": "18/01/2009", "winninghistoryp13dprize": "3rd", "winninghistoryp23d": "23/10/2005", "winninghistoryp23dprize": "2nd", "winninghistoryp33d": "-", "winninghistoryp33dprize": "-", "winninghistoryp13p3d": "-", "winninghistoryp13p3dprize": "-", "winninghistoryp23p3d": "-", "winninghistoryp23p3dprize": "-", "winninghistoryp33p3d": "-", "winninghistoryp33p3dprize": "-"}