{"id": "843", "status": "C", "NewGame": "0", "drawDate": "19/12/2009", "p1HorseNo": "", "p2HorseNo": "", "p3HorseNo": "", "drawNo": "3224/09", "starterHorseList": ["", "", "", "", "", "", "", "", "", ""], "consolidateList": ["5904", "9854", "1940", "6733", "2261", "8452", "1556", "0167", "1555", "8177"], "starterList": ["1086", "0607", "8308", "4457", "8728", "7882", "1042", "2134", "5662", "9506"], "1+3DJackpot1": "0.00", "1+3DJackpot2": "0.00", "dmcJackpot1": "0.00", "dmcJackpot2": "0.00", "3DJackpot": "0.00", "1+3DJackpotWinning1": "0", "1+3DJackpotWinning2": "0", "3DJackpotWinning": "0", "dmcJackpotWinning1": "0", "dmcJackpotWinning2": "0", "drawVenue": "PERAK TURF CLUB", "raceNo": "", "raceVenue": "", "p1": "8847", "p2": "0235", "p3": "7770", "consolidateList3p3d": [], "starterList3p3d": [], "p13p3d": "", "p23p3d": "", "p33p3d": "", "zodiac3dp1": "", "zodiac3dp2": "", "zodiac3dp3": "", "3+3DBonusp1": "300,000.00", "3+3DBonusp2": "100,000.00", "3+3DBonusp3": "30,000.00", "3+3DBonusp1Winning": "0", "3+3DBonusp2Winning": "0", "3+3DBonusp3Winning": "0", "winninghistoryconsolidateList": ["26/05/2009", "29/07/2009", "-", "15/03/2006", "-", "-", "23/05/2009", "11/07/2007", "11/03/2009", "08/08/2009"], "winninghistoryconsolidateListPrize": ["Consolation", "Starter", "-", "Consolation", "-", "-", "Consolation", "Starter", "Consolation", "Starter"], "winninghistorystarterList": ["-", "27/11/2007", "15/02/2009", "03/12/2005", "19/04/2005", "28/03/2009", "09/07/2008", "28/09/2008", "-", "15/10/2008"], "winninghistorystarterListPrize": ["-", "Starter", "Consolation", "Starter", "Starter", "Starter", "Starter", "Starter", "-", "Starter"], "winninghistoryconsolidateList3p3d": ["-", "-", "-", "-", "-", "-", "-", "-", "-", "-"], "winninghistoryconsolidateList3p3dPrize": ["-", "-", "-", "-", "-", "-", "-", "-", "-", "-"], "winninghistorystarterList3p3d": ["-", "-", "-", "-", "-", "-", "-", "-", "-", "-"], "winninghistorystaterList3p3dPrize": ["-", "-", "-", "-", "-", "-", "-", "-", "-", "-"], "winninghistoryp1": "01/02/2005", "winninghistoryp1prize": "2nd", "winninghistoryp2": "15/12/2009", "winninghistoryp2prize": "Consolation", "winninghistoryp3": "13/09/2009", "winninghistoryp3prize": "Starter", "winninghistoryp13d": "04/10/2008", "winninghistoryp13dprize": "3rd", "winninghistoryp23d": "24/09/2008", "winninghistoryp23dprize": "1st", "winninghistoryp33d": "02/04/2008", "winninghistoryp33dprize": "2nd", "winninghistoryp13p3d": "-", "winninghistoryp13p3dprize": "-", "winninghistoryp23p3d": "-", "winninghistoryp23p3dprize": "-", "winninghistoryp33p3d": "-", "winninghistoryp33p3dprize": "-"}