{"id": "569", "status": "C", "NewGame": "0", "drawDate": "10/05/2008", "p1HorseNo": "", "p2HorseNo": "", "p3HorseNo": "", "drawNo": "2950/08", "starterHorseList": ["", "", "", "", "", "", "", "", "", ""], "consolidateList": ["6627", "8961", "2216", "8920", "6091", "3637", "3214", "6167", "1523", "0524"], "starterList": ["0981", "9096", "4684", "7106", "3658", "2871", "2877", "5606", "9064", "1530"], "1+3DJackpot1": "0.00", "1+3DJackpot2": "0.00", "dmcJackpot1": "0.00", "dmcJackpot2": "0.00", "3DJackpot": "0.00", "1+3DJackpotWinning1": "0", "1+3DJackpotWinning2": "0", "3DJackpotWinning": "0", "dmcJackpotWinning1": "0", "dmcJackpotWinning2": "0", "drawVenue": "PERAK TURF CLUB", "raceNo": "", "raceVenue": "", "p1": "3613", "p2": "3573", "p3": "6635", "consolidateList3p3d": [], "starterList3p3d": [], "p13p3d": "", "p23p3d": "", "p33p3d": "", "zodiac3dp1": "", "zodiac3dp2": "", "zodiac3dp3": "", "3+3DBonusp1": "300,000.00", "3+3DBonusp2": "100,000.00", "3+3DBonusp3": "30,000.00", "3+3DBonusp1Winning": "0", "3+3DBonusp2Winning": "0", "3+3DBonusp3Winning": "0", "winninghistoryconsolidateList": ["07/11/2006", "-", "26/07/2006", "19/09/2007", "09/01/2005", "-", "-", "19/04/2008", "13/05/2006", "-"], "winninghistoryconsolidateListPrize": ["Consolation", "-", "Consolation", "Consolation", "Starter", "-", "-", "Starter", "Starter", "-"], "winninghistorystarterList": ["25/08/2007", "07/10/2006", "29/07/2007", "16/03/2005", "-", "07/11/2007", "29/07/2007", "-", "28/07/2007", "10/06/2006"], "winninghistorystarterListPrize": ["Consolation", "Starter", "Consolation", "Consolation", "-", "Consolation", "Starter", "-", "Consolation", "Starter"], "winninghistoryconsolidateList3p3d": ["-", "-", "-", "-", "-", "-", "-", "-", "-", "-"], "winninghistoryconsolidateList3p3dPrize": ["-", "-", "-", "-", "-", "-", "-", "-", "-", "-"], "winninghistorystarterList3p3d": ["-", "-", "-", "-", "-", "-", "-", "-", "-", "-"], "winninghistorystaterList3p3dPrize": ["-", "-", "-", "-", "-", "-", "-", "-", "-", "-"], "winninghistoryp1": "05/09/2006", "winninghistoryp1prize": "Consolation", "winninghistoryp2": "25/11/2007", "winninghistoryp2prize": "Starter", "winninghistoryp3": "22/01/2005", "winninghistoryp3prize": "2nd", "winninghistoryp13d": "21/09/2005", "winninghistoryp13dprize": "1st", "winninghistoryp23d": "26/03/2005", "winninghistoryp23dprize": "2nd", "winninghistoryp33d": "15/01/2006", "winninghistoryp33dprize": "3rd", "winninghistoryp13p3d": "-", "winninghistoryp13p3dprize": "-", "winninghistoryp23p3d": "-", "winninghistoryp23p3dprize": "-", "winninghistoryp33p3d": "-", "winninghistoryp33p3dprize": "-"}