{"id": "3014", "status": "COMPLETED", "NewGame": "1", "drawDate": "16/10/2022", "p1HorseNo": "13", "p2HorseNo": "3", "p3HorseNo": "7", "drawNo": "5482/22", "starterHorseList": ["5", "11", "12", "1", "9", "6", "2", "8", "4", "10"], "consolidateList": ["9244", "2342", "4407", "2910", "3321", "7867", "7206", "5382", "5904", "1161"], "starterList": ["4407", "5781", "2017", "6286", "3043", "8398", "6709", "5528", "5429", "1622"], "1+3DJackpot1": "30,230,600.00", "1+3DJackpot2": "280,922.40", "dmcJackpot1": "", "dmcJackpot2": "", "3DJackpot": "943,586.10", "1+3DJackpotWinning1": "2", "1+3DJackpotWinning2": "2", "3DJackpotWinning": "0", "dmcJackpotWinning1": "0", "dmcJackpotWinning2": "0", "drawVenue": "PERAK TURF CLUB", "raceDate": "09/10/2022", "raceNo": "7", "raceVenue": "HONG KONG JOCKEY CLUB", "p1": "9363", "p2": "7835", "p3": "2919", "consolidateList3p3d": ["129244", "362342", "624407", "272910", "863321", "317867", "347206", "265382", "655904", "201161"], "starterList3p3d": ["964407", "645781", "502017", "796286", "703043", "068398", "476709", "975528", "125429", "931622"], "p13p3d": "189363", "p23p3d": "127835", "p33p3d": "902919", "zodiac3dp1": "12", "zodiac3dp2": "1", "zodiac3dp3": "12", "3+3DBonusp1": "2,503,333.30", "3+3DBonusp2": "541,666.60", "3+3DBonusp3": "2,060,000.00", "3+3DBonusp1Winning": "0", "3+3DBonusp2Winning": "0", "3+3DBonusp3Winning": "2", "winninghistoryconsolidateList": ["17/04/2022", "27/06/2015", "26/04/2011", "15/09/2021", "26/07/2015", "19/07/2017", "17/02/2018", "05/10/2021", "02/06/2019", "22/07/2017"], "winninghistoryconsolidateListPrize": ["Starter", "Starter", "Starter", "Consolation", "Consolation", "Starter", "Consolation", "Consolation", "Starter", "Consolation"], "winninghistorystarterList": ["26/04/2011", "27/11/2019", "15/01/2020", "12/09/2010", "19/01/2022", "27/09/2020", "02/02/2022", "19/08/2015", "27/03/2022", "05/10/2019"], "winninghistorystarterListPrize": ["Starter", "Consolation", "Starter", "Consolation", "Starter", "Starter", "Consolation", "Consolation", "Starter", "Consolation"], "winninghistoryconsolidateList3p3d": ["-", "-", "-", "-", "-", "-", "-", "-", "-", "-"], "winninghistoryconsolidateList3p3dPrize": ["-", "-", "-", "-", "-", "-", "-", "-", "-", "-"], "winninghistorystarterList3p3d": ["-", "-", "-", "-", "-", "-", "-", "-", "27/03/2022", "-"], "winninghistorystarterList3p3dPrize": ["-", "-", "-", "-", "-", "-", "-", "-", "Starter", "-"], "winninghistoryp1": "25/10/2020", "winninghistoryp1prize": "Consolation", "winninghistoryp2": "29/09/2019", "winninghistoryp2prize": "Starter", "winninghistoryp3": "18/06/2022", "winninghistoryp3prize": "Starter", "winninghistoryp13d": "02/12/2018", "winninghistoryp13dprize": "1st", "winninghistoryp23d": "08/11/2020", "winninghistoryp23dprize": "1st", "winninghistoryp33d": "27/06/2020", "winninghistoryp33dprize": "1st", "winninghistoryp13p3d": "-", "winninghistoryp13p3dprize": "-", "winninghistoryp23p3d": "-", "winninghistoryp23p3dprize": "-", "winninghistoryp33p3d": "-", "winninghistoryp33p3dprize": "-", "oneplusthreedjackpot1msg": "16/10/2022 (Sun) - The 1+3D Jackpot 1 amount of RM824,675.65 has been won on HSSB268, HSSB388, HSSB408, HSSB336, HSSB290 and HSSB84 in Selangor.", "oneplusthreedjackpot2msg": "16/10/2022 (Sun) - The 1+3D Jackpot 2 amount of RM135,256.10 has been won on HSSB10, HSSB600, HSSB268, HSSB178, HSSB304, HSSB260, HSSB288, HSSB310, HSSB258, HSSB292, HSSB98, HSSB298, HSSB236, HSSB308, HSSB274, HSSB296, HSSB336, HSSB88, HSSB290, HSSB320, HSSB420, HSSB84, HSSB24, HSSB300, HSSB160, HSSB244, HSSB250, HSSB354, HSSB342, HSSB276, HSSB318, HSSB334, HSSB174, HSSB192, HSSB450, HSSB108, HSSB272, HSSB74, HSSB72, HSSB100, HSSB186 and HSSB150 in Pulau Pinang, Selangor, Johor, Perak and from dmcGO.", "dmcwinnerstatus4msg": "", "dmcwinnerstatus5msg": "", "threedjackpotmsg": "", "threeplustatus1bonusmsg": "", "threeplustatus2bonusmsg": "", "threeplustatus3bonusmsg": "16/10/2022 (Sun) -  The 3+3D 3rd Prize Bonus amount of RM171,666.70 has been won on Straight Bet from dmcGO."}