{"id": "959", "status": "C", "NewGame": "0", "drawDate": "14/08/2010", "p1HorseNo": "", "p2HorseNo": "", "p3HorseNo": "", "drawNo": "3340/10", "starterHorseList": ["", "", "", "", "", "", "", "", "", ""], "consolidateList": ["4724", "3704", "0147", "4649", "9407", "7644", "3698", "4806", "9998", "9117"], "starterList": ["3846", "0468", "1379", "6831", "9692", "2571", "9672", "7683", "6929", "7691"], "1+3DJackpot1": "0.00", "1+3DJackpot2": "0.00", "dmcJackpot1": "0.00", "dmcJackpot2": "0.00", "3DJackpot": "0.00", "1+3DJackpotWinning1": "0", "1+3DJackpotWinning2": "0", "3DJackpotWinning": "0", "dmcJackpotWinning1": "0", "dmcJackpotWinning2": "0", "drawVenue": "PERAK TURF CLUB", "raceNo": "", "raceVenue": "", "p1": "2485", "p2": "4897", "p3": "6605", "consolidateList3p3d": [], "starterList3p3d": [], "p13p3d": "", "p23p3d": "", "p33p3d": "", "zodiac3dp1": "", "zodiac3dp2": "", "zodiac3dp3": "", "3+3DBonusp1": "300,000.00", "3+3DBonusp2": "100,000.00", "3+3DBonusp3": "30,000.00", "3+3DBonusp1Winning": "0", "3+3DBonusp2Winning": "0", "3+3DBonusp3Winning": "0", "winninghistoryconsolidateList": ["29/10/2006", "22/01/2005", "02/07/2005", "24/07/2010", "26/01/2008", "01/12/2009", "05/11/2008", "21/11/2007", "07/01/2006", "23/02/2008"], "winninghistoryconsolidateListPrize": ["Starter", "Starter", "2nd", "1st", "Consolation", "Starter", "Starter", "1st", "Starter", "Starter"], "winninghistorystarterList": ["14/10/2007", "30/03/2010", "14/12/2008", "28/06/2006", "27/02/2010", "08/02/2009", "23/07/2005", "26/09/2007", "30/11/2005", "-"], "winninghistorystarterListPrize": ["Starter", "2nd", "Starter", "1st", "Consolation", "Starter", "Consolation", "Consolation", "Consolation", "-"], "winninghistoryconsolidateList3p3d": ["-", "-", "-", "-", "-", "-", "-", "-", "-", "-"], "winninghistoryconsolidateList3p3dPrize": ["-", "-", "-", "-", "-", "-", "-", "-", "-", "-"], "winninghistorystarterList3p3d": ["-", "-", "-", "-", "-", "-", "-", "-", "-", "-"], "winninghistorystaterList3p3dPrize": ["-", "-", "-", "-", "-", "-", "-", "-", "-", "-"], "winninghistoryp1": "22/02/2009", "winninghistoryp1prize": "Consolation", "winninghistoryp2": "06/06/2007", "winninghistoryp2prize": "1st", "winninghistoryp3": "06/12/2006", "winninghistoryp3prize": "1st", "winninghistoryp13d": "09/07/2008", "winninghistoryp13dprize": "3rd", "winninghistoryp23d": "02/01/2008", "winninghistoryp23dprize": "1st", "winninghistoryp33d": "23/07/2008", "winninghistoryp33dprize": "1st", "winninghistoryp13p3d": "-", "winninghistoryp13p3dprize": "-", "winninghistoryp23p3d": "-", "winninghistoryp23p3dprize": "-", "winninghistoryp33p3d": "-", "winninghistoryp33p3dprize": "-"}