{"id": "2599", "status": "COMPLETED", "NewGame": "1", "drawDate": "06/10/2019", "p1HorseNo": "1", "p2HorseNo": "10", "p3HorseNo": "8", "drawNo": "4961/19", "starterHorseList": ["13", "12", "6", "7", "5", "3", "11", "9", "2", "4"], "consolidateList": ["8800", "8259", "0187", "8325", "3189", "8779", "7491", "8485", "2647", "1662"], "starterList": ["0869", "4481", "4736", "6086", "4947", "8412", "9082", "4723", "6636", "8895"], "1+3DJackpot1": "6,035,843.80", "1+3DJackpot2": "100,000.00", "dmcJackpot1": "", "dmcJackpot2": "", "3DJackpot": "738,928.70", "1+3DJackpotWinning1": "0", "1+3DJackpotWinning2": "0", "3DJackpotWinning": "0", "dmcJackpotWinning1": "0", "dmcJackpotWinning2": "0", "drawVenue": "PERAK TURF CLUB", "raceDate": "02/10/2019", "raceNo": "9", "raceVenue": "AUSTRALIA", "p1": "1626", "p2": "0094", "p3": "0382", "consolidateList3p3d": ["208800", "398259", "810187", "098325", "863189", "698779", "707491", "488485", "822647", "331662"], "starterList3p3d": ["780869", "884481", "364736", "106086", "894947", "478412", "759082", "274723", "236636", "938895"], "p13p3d": "431626", "p23p3d": "240094", "p33p3d": "560382", "zodiac3dp1": "6", "zodiac3dp2": "10", "zodiac3dp3": "4", "3+3DBonusp1": "1,378,224.10", "3+3DBonusp2": "2,869,833.30", "3+3DBonusp3": "684,722.10", "3+3DBonusp1Winning": "0", "3+3DBonusp2Winning": "0", "3+3DBonusp3Winning": "0", "winninghistoryconsolidateList": ["07/08/2019", "16/05/2015", "19/09/2018", "26/05/2018", "12/04/2017", "01/07/2018", "26/12/2018", "23/11/2014", "30/06/2019", "26/05/2018"], "winninghistoryconsolidateListPrize": ["Consolation", "Consolation", "Starter", "Starter", "Consolation", "Consolation", "Consolation", "Consolation", "Consolation", "Consolation"], "winninghistorystarterList": ["22/02/2017", "15/07/2017", "21/06/2014", "06/02/2016", "29/05/2019", "31/08/2014", "21/04/2019", "19/04/2017", "25/03/2018", "11/07/2018"], "winninghistorystarterListPrize": ["Consolation", "2nd", "Consolation", "Starter", "Consolation", "3rd", "Consolation", "2nd", "Starter", "Consolation"], "winninghistoryconsolidateList3p3d": ["-", "-", "-", "-", "-", "-", "-", "-", "-", "-"], "winninghistoryconsolidateList3p3dPrize": ["-", "-", "-", "-", "-", "-", "-", "-", "-", "-"], "winninghistorystarterList3p3d": ["-", "-", "-", "-", "-", "-", "-", "-", "-", "-"], "winninghistorystarterList3p3dPrize": ["-", "-", "-", "-", "-", "-", "-", "-", "-", "-"], "winninghistoryp1": "18/09/2019", "winninghistoryp1prize": "Starter", "winninghistoryp2": "24/04/2019", "winninghistoryp2prize": "3rd", "winninghistoryp3": "09/03/2019", "winninghistoryp3prize": "Consolation", "winninghistoryp13d": "21/04/2018", "winninghistoryp13dprize": "2nd", "winninghistoryp23d": "24/04/2019", "winninghistoryp23dprize": "3rd", "winninghistoryp33d": "18/04/2018", "winninghistoryp33dprize": "2nd", "winninghistoryp13p3d": "-", "winninghistoryp13p3dprize": "-", "winninghistoryp23p3d": "-", "winninghistoryp23p3dprize": "-", "winninghistoryp33p3d": "09/03/2019", "winninghistoryp33p3dprize": "Consolation", "oneplusthreedjackpot1msg": "", "oneplusthreedjackpot2msg": "", "dmcwinnerstatus4msg": "", "dmcwinnerstatus5msg": "", "threedjackpotmsg": "", "threeplustatus1bonusmsg": "", "threeplustatus2bonusmsg": "", "threeplustatus3bonusmsg": ""}