{"id": "216", "status": "C", "NewGame": "0", "drawDate": "28/03/2006", "p1HorseNo": "", "p2HorseNo": "", "p3HorseNo": "", "drawNo": "2597/06", "starterHorseList": ["", "", "", "", "", "", "", "", "", ""], "consolidateList": ["3260", "0465", "9637", "9642", "5578", "4134", "3033", "1274", "5503", "7698"], "starterList": ["2874", "3227", "9211", "4607", "1947", "9794", "1885", "9314", "8673", "6792"], "1+3DJackpot1": "0.00", "1+3DJackpot2": "0.00", "dmcJackpot1": "0.00", "dmcJackpot2": "0.00", "3DJackpot": "0.00", "1+3DJackpotWinning1": "0", "1+3DJackpotWinning2": "0", "3DJackpotWinning": "0", "dmcJackpotWinning1": "0", "dmcJackpotWinning2": "0", "drawVenue": "SELANGOR TURF CLUB", "raceNo": "", "raceVenue": "", "p1": "7009", "p2": "2901", "p3": "3588", "consolidateList3p3d": [], "starterList3p3d": [], "p13p3d": "", "p23p3d": "", "p33p3d": "", "zodiac3dp1": "", "zodiac3dp2": "", "zodiac3dp3": "", "3+3DBonusp1": "300,000.00", "3+3DBonusp2": "100,000.00", "3+3DBonusp3": "30,000.00", "3+3DBonusp1Winning": "0", "3+3DBonusp2Winning": "0", "3+3DBonusp3Winning": "0", "winninghistoryconsolidateList": ["-", "15/05/2005", "-", "-", "08/03/2005", "03/12/2005", "-", "-", "-", "-"], "winninghistoryconsolidateListPrize": ["-", "Starter", "-", "-", "Starter", "Consolation", "-", "-", "-", "-"], "winninghistorystarterList": ["-", "27/07/2005", "-", "13/11/2005", "25/12/2005", "21/08/2005", "-", "-", "-", "-"], "winninghistorystarterListPrize": ["-", "Starter", "-", "2nd", "Consolation", "Starter", "-", "-", "-", "-"], "winninghistoryconsolidateList3p3d": ["-", "-", "-", "-", "-", "-", "-", "-", "-", "-"], "winninghistoryconsolidateList3p3dPrize": ["-", "-", "-", "-", "-", "-", "-", "-", "-", "-"], "winninghistorystarterList3p3d": ["-", "-", "-", "-", "-", "-", "-", "-", "-", "-"], "winninghistorystaterList3p3dPrize": ["-", "-", "-", "-", "-", "-", "-", "-", "-", "-"], "winninghistoryp1": "22/10/2005", "winninghistoryp1prize": "Starter", "winninghistoryp2": "09/01/2005", "winninghistoryp2prize": "Consolation", "winninghistoryp3": "14/09/2005", "winninghistoryp3prize": "Starter", "winninghistoryp13d": "-", "winninghistoryp13dprize": "-", "winninghistoryp23d": "03/07/2005", "winninghistoryp23dprize": "2nd", "winninghistoryp33d": "10/08/2005", "winninghistoryp33dprize": "1st", "winninghistoryp13p3d": "-", "winninghistoryp13p3dprize": "-", "winninghistoryp23p3d": "-", "winninghistoryp23p3dprize": "-", "winninghistoryp33p3d": "-", "winninghistoryp33p3dprize": "-"}