{"id": "3365", "status": "COMPLETED", "NewGame": "1", "drawDate": "20/11/2024", "p1HorseNo": "6", "p2HorseNo": "10", "p3HorseNo": "13", "drawNo": "5833/24", "starterHorseList": ["4", "3", "11", "12", "9", "2", "5", "7", "1", "8"], "consolidateList": ["2122", "5025", "4783", "3849", "4627", "7265", "2797", "4869", "3161", "5806"], "starterList": ["7574", "6096", "8706", "6226", "1580", "8442", "5763", "9010", "6959", "9333"], "1+3DJackpot1": "10,491,140.80", "1+3DJackpot2": "237,113.50", "dmcJackpot1": "", "dmcJackpot2": "", "3DJackpot": "694,320.20", "1+3DJackpotWinning1": "0", "1+3DJackpotWinning2": "2", "3DJackpotWinning": "0", "dmcJackpotWinning1": "0", "dmcJackpotWinning2": "0", "drawVenue": "WISMA GENTING, KL", "raceDate": "17/11/2024", "raceNo": "6", "raceVenue": "HONG KONG JOCKEY CLUB", "p1": "5947", "p2": "8631", "p3": "1547", "consolidateList3p3d": ["412122", "355025", "594783", "113849", "744627", "657265", "592797", "754869", "083161", "805806"], "starterList3p3d": ["097574", "276096", "828706", "096226", "021580", "338442", "765763", "989010", "066959", "689333"], "p13p3d": "885947", "p23p3d": "478631", "p33p3d": "311547", "zodiac3dp1": "2", "zodiac3dp2": "10", "zodiac3dp3": "6", "3+3DBonusp1": "1,176,410.40", "3+3DBonusp2": "955,532.30", "3+3DBonusp3": "1,496,188.40", "3+3DBonusp1Winning": "0", "3+3DBonusp2Winning": "0", "3+3DBonusp3Winning": "0", "winninghistoryconsolidateList": ["02/11/2024", "06/04/2024", "21/04/2019", "16/09/2020", "04/06/2023", "26/07/2022", "06/09/2022", "01/08/2017", "22/01/2017", "14/08/2024"], "winninghistoryconsolidateListPrize": ["Starter", "Consolation", "Consolation", "Consolation", "Starter", "Consolation", "Consolation", "Starter", "Starter", "Consolation"], "winninghistorystarterList": ["26/06/2022", "18/02/2024", "16/08/2020", "23/01/2022", "04/09/2024", "16/02/2021", "29/04/2023", "26/10/2022", "03/11/2020", "26/08/2020"], "winninghistorystarterListPrize": ["Consolation", "Starter", "2nd", "Consolation", "Consolation", "Consolation", "Consolation", "Starter", "Starter", "Starter"], "winninghistoryconsolidateList3p3d": ["-", "-", "-", "-", "-", "-", "06/09/2022", "-", "-", "-"], "winninghistoryconsolidateList3p3dPrize": ["-", "-", "-", "-", "-", "-", "Consolation", "-", "-", "-"], "winninghistorystarterList3p3d": ["-", "-", "-", "-", "-", "-", "-", "-", "-", "-"], "winninghistorystarterList3p3dPrize": ["-", "-", "-", "-", "-", "-", "-", "-", "-", "-"], "winninghistoryp1": "24/02/2021", "winninghistoryp1prize": "Starter", "winninghistoryp2": "04/01/2017", "winninghistoryp2prize": "Consolation", "winninghistoryp3": "15/05/2019", "winninghistoryp3prize": "Starter", "winninghistoryp13d": "01/07/2018", "winninghistoryp13dprize": "3rd", "winninghistoryp23d": "20/05/2023", "winninghistoryp23dprize": "2nd", "winninghistoryp33d": "14/06/2023", "winninghistoryp33dprize": "3rd", "winninghistoryp13p3d": "-", "winninghistoryp13p3dprize": "-", "winninghistoryp23p3d": "-", "winninghistoryp23p3dprize": "-", "winninghistoryp33p3d": "-", "winninghistoryp33p3dprize": "-", "oneplusthreedjackpot1msg": "", "oneplusthreedjackpot2msg": "20/11/2024 (Wed) - The 1+3D Jackpot 2 amount of RM34,369.50 has been won on HSSB190, HSSB10 and HSSB44 in Kuala Lumpur and from dmcGO.", "dmcwinnerstatus4msg": "", "dmcwinnerstatus5msg": "", "threedjackpotmsg": "", "threeplustatus1bonusmsg": "", "threeplustatus2bonusmsg": "", "threeplustatus3bonusmsg": ""}