{"id": "1798", "status": "C", "NewGame": "0", "drawDate": "05/05/2015", "p1HorseNo": "7", "p2HorseNo": "4", "p3HorseNo": "3", "drawNo": "4181/15", "starterHorseList": ["13", "9", "8", "10", "12", "5", "2", "1", "6", "11"], "consolidateList": ["6229", "2605", "3935", "6039", "6642", "7935", "4002", "2991", "6662", "9364"], "starterList": ["2837", "6176", "9602", "2670", "6672", "2302", "9107", "5934", "5048", "7106"], "1+3DJackpot1": "21,074,391.80", "1+3DJackpot2": "174,143.70", "dmcJackpot1": "2,315,263.10", "dmcJackpot2": "187,970.50", "3DJackpot": "1,661,220.40", "1+3DJackpotWinning1": "0", "1+3DJackpotWinning2": "0", "3DJackpotWinning": "0", "dmcJackpotWinning1": "0", "dmcJackpotWinning2": "0", "drawVenue": "PERAK TURF CLUB", "raceNo": "4", "raceVenue": "HONG KONG JOCKEY CLUB", "p1": "8076", "p2": "4875", "p3": "5029", "consolidateList3p3d": [], "starterList3p3d": [], "p13p3d": "", "p23p3d": "", "p33p3d": "", "zodiac3dp1": "", "zodiac3dp2": "", "zodiac3dp3": "", "3+3DBonusp1": "300,000.00", "3+3DBonusp2": "100,000.00", "3+3DBonusp3": "30,000.00", "3+3DBonusp1Winning": "0", "3+3DBonusp2Winning": "0", "3+3DBonusp3Winning": "0", "winninghistoryconsolidateList": ["11/04/2015", "01/11/2006", "25/03/2014", "-", "11/03/2015", "29/03/2014", "-", "15/06/2013", "24/05/2014", "23/11/2014"], "winninghistoryconsolidateListPrize": ["Starter", "Consolation", "Consolation", "-", "3rd", "2nd", "-", "Consolation", "2nd", "Consolation"], "winninghistorystarterList": ["31/05/2009", "18/02/2015", "18/07/2012", "03/12/2011", "17/03/2013", "13/09/2014", "09/11/2011", "14/11/2010", "05/08/2014", "03/08/2013"], "winninghistorystarterListPrize": ["Starter", "Starter", "Starter", "3rd", "Starter", "2nd", "Starter", "Consolation", "Starter", "Consolation"], "winninghistoryconsolidateList3p3d": ["-", "-", "-", "-", "-", "-", "-", "-", "-", "-"], "winninghistoryconsolidateList3p3dPrize": ["-", "-", "-", "-", "-", "-", "-", "-", "-", "-"], "winninghistorystarterList3p3d": ["-", "-", "-", "-", "-", "-", "-", "-", "-", "-"], "winninghistorystaterList3p3dPrize": ["-", "-", "-", "-", "-", "-", "-", "-", "-", "-"], "winninghistoryp1": "01/03/2014", "winninghistoryp1prize": "Starter", "winninghistoryp2": "25/07/2012", "winninghistoryp2prize": "Starter", "winninghistoryp3": "09/02/2014", "winninghistoryp3prize": "3rd", "winninghistoryp13d": "11/01/2015", "winninghistoryp13dprize": "1st", "winninghistoryp23d": "19/02/2013", "winninghistoryp23dprize": "1st", "winninghistoryp33d": "02/08/2014", "winninghistoryp33dprize": "3rd", "winninghistoryp13p3d": "-", "winninghistoryp13p3dprize": "-", "winninghistoryp23p3d": "-", "winninghistoryp23p3dprize": "-", "winninghistoryp33p3d": "-", "winninghistoryp33p3dprize": "-"}